<?xml version="1.0" encoding="UTF-8"?>

<world
    xmlns:xsi='http://www.w3.org/2001/XMLSchema-instance'
    xsi:noNamespaceSchemaLocation='jaxb/worldSchema/worldSchema.xsd'>
    <name>Football Capitalist</name>
    <logo>img/logo.png</logo>
    <money>1500</money>
    <score>0</score>
    <totalangels>0</totalangels>
    <activeangels>0</activeangels>
    <angelbonus>0</angelbonus>
    <lastupdate>0</lastupdate>
    <products>
        <product>
            <id>1</id>
            <name>Gardien</name>
            <logo>img/products/1.png</logo>
            <cout>1</cout>
            <croissance>7</croissance>
            <revenu>1</revenu>
            <vitesse>10000</vitesse>
            <quantite>0</quantite>
            <timeleft>0</timeleft>
            <managerUnlocked>false</managerUnlocked>
            <palliers>
                <pallier>
                    <name>Gardien réserviste</name>
                    <logo>img/products/1/1.png</logo>
                    <seuil>5</seuil>
                    <idcible>1</idcible>
                    <ratio>1.5</ratio>
                    <typeratio>gain</typeratio>
                    <unlocked>false</unlocked>
                </pallier>
                <pallier>
                    <name>Gardien remplaçant</name>
                    <logo>img/products/1/2.png</logo>
                    <seuil>10</seuil>
                    <idcible>1</idcible>
                    <ratio>2</ratio>
                    <typeratio>vitesse</typeratio>
                    <unlocked>false</unlocked>
                </pallier>
                <pallier>
                    <name>Gardien titulaire</name>
                    <logo>img/products/1/3.png</logo>
                    <seuil>20</seuil>
                    <idcible>1</idcible>
                    <ratio>3</ratio>
                    <typeratio>gain</typeratio>
                    <unlocked>false</unlocked>
                </pallier>
                <pallier>
                    <name>Un arrêt decisif</name>
                    <logo>img/products/1/4.png</logo>
                    <seuil>25</seuil>
                    <idcible>1</idcible>
                    <ratio>3</ratio>
                    <typeratio>gain</typeratio>
                    <unlocked>false</unlocked>
                </pallier>
                <pallier>
                    <name>Gardien de l'équipe nationale</name>
                    <logo>img/products/1/5.png</logo>
                    <seuil>30</seuil>
                    <idcible>1</idcible>
                    <ratio>3</ratio>
                    <typeratio>gain</typeratio>
                    <unlocked>false</unlocked>
                </pallier>
                <pallier>
                    <name>Le gant d'or</name>
                    <logo>img/products/1/6.png</logo>
                    <seuil>35</seuil>
                    <idcible>1</idcible>
                    <ratio>2</ratio>
                    <typeratio>gain</typeratio>
                    <unlocked>false</unlocked>
                </pallier>
                <pallier>
                    <name>Gardien champion d'Europe</name>
                    <logo>img/products/1/7.png</logo>
                    <seuil>45</seuil>
                    <idcible>1</idcible>
                    <ratio>2</ratio>
                    <typeratio>gain</typeratio>
                    <unlocked>false</unlocked>
                </pallier>
                <pallier>
                    <name>Gardien champion du monde</name>
                    <logo>img/products/1/8.png</logo>
                    <seuil>50</seuil>
                    <idcible>1</idcible>
                    <ratio>3</ratio>
                    <typeratio>gain</typeratio>
                    <unlocked>false</unlocked>
                </pallier>
                <pallier>
                    <name>Meilleur gardien du monde</name>
                    <logo>img/products/1/9.png</logo>
                    <seuil>60</seuil>
                    <idcible>1</idcible>
                    <ratio>2</ratio>
                    <typeratio>vitesse</typeratio>
                    <unlocked>false</unlocked>
                </pallier>
            </palliers>
        </product>
        <product>
            <id>2</id>
            <name>Défenseur</name>
            <logo>img/products/2.png</logo>
            <cout>70</cout>
            <croissance>15</croissance>
            <revenu>10</revenu>
            <vitesse>60000</vitesse>
            <quantite>0</quantite>
            <timeleft>0</timeleft>
            <managerUnlocked>false</managerUnlocked>
            <palliers>
                <pallier>
                    <name>Défenseur réserviste</name>
                    <logo>img/products/2/1.png</logo>
                    <seuil>10</seuil>
                    <idcible>2</idcible>
                    <ratio>1.5</ratio>
                    <typeratio>gain</typeratio>
                    <unlocked>false</unlocked>
                </pallier>
                <pallier>
                    <name>Défenseur remplaçant</name>
                    <logo>img/products/2/2.png</logo>
                    <seuil>25</seuil>
                    <idcible>2</idcible>
                    <ratio>2</ratio>
                    <typeratio>vitesse</typeratio>
                    <unlocked>false</unlocked>
                </pallier>
                <pallier>
                    <name>Défenseur titulaire</name>
                    <logo>img/products/2/3.png</logo>
                    <seuil>50</seuil>
                    <idcible>2</idcible>
                    <ratio>3</ratio>
                    <typeratio>gain</typeratio>
                    <unlocked>false</unlocked>
                </pallier>
                <pallier>
                    <name>Tacle assassin</name>
                    <logo>img/products/2/4.png</logo>
                    <seuil>75</seuil>
                    <idcible>2</idcible>
                    <ratio>3</ratio>
                    <typeratio>vitesse</typeratio>
                    <unlocked>false</unlocked>
                </pallier>
                <pallier>
                    <name>Défenseur de l'équipe nationale</name>
                    <logo>img/products/2/5.png</logo>
                    <seuil>100</seuil>
                    <idcible>2</idcible>
                    <ratio>3</ratio>
                    <typeratio>gain</typeratio>
                    <unlocked>false</unlocked>
                </pallier>
                <pallier>
                    <name>Sauvetage sur la ligne</name>
                    <logo>img/products/2/6.png</logo>
                    <seuil>150</seuil>
                    <idcible>2</idcible>
                    <ratio>2</ratio>
                    <typeratio>vitesse</typeratio>
                    <unlocked>false</unlocked>
                </pallier>
                <pallier>
                    <name>Défenseur champion d'Europe</name>
                    <logo>img/products/2/7.png</logo>
                    <seuil>200</seuil>
                    <idcible>2</idcible>
                    <ratio>2</ratio>
                    <typeratio>gain</typeratio>
                    <unlocked>false</unlocked>
                </pallier>
                <pallier>
                    <name>Défenseur champion du monde</name>
                    <logo>img/products/2/8.png</logo>
                    <seuil>300</seuil>
                    <idcible>2</idcible>
                    <ratio>3</ratio>
                    <typeratio>gain</typeratio>
                    <unlocked>false</unlocked>
                </pallier>
                <pallier>
                    <name>Meilleur défenseur du monde</name>
                    <logo>img/products/2/9.png</logo>
                    <seuil>400</seuil>
                    <idcible>2</idcible>
                    <ratio>2</ratio>
                    <typeratio>vitesse</typeratio>
                    <unlocked>false</unlocked>
                </pallier>
            </palliers>
        </product>
        <product>
            <id>3</id>
            <name>Milieu de terrain</name>
            <logo>img/products/3.png</logo>
            <cout>720</cout>
            <croissance>14</croissance>
            <revenu>540</revenu>
            <vitesse>300000</vitesse>
            <quantite>0</quantite>
            <timeleft>0</timeleft>
            <managerUnlocked>false</managerUnlocked>
            <palliers>
                <pallier>
                    <name>Milieu réserviste</name>
                    <logo>img/products/3/1.png</logo>
                    <seuil>10</seuil>
                    <idcible>3</idcible>
                    <ratio>1.5</ratio>
                    <typeratio>gain</typeratio>
                    <unlocked>false</unlocked>
                </pallier>
                <pallier>
                    <name>Milieu remplaçant</name>
                    <logo>img/products/3/2.png</logo>
                    <seuil>25</seuil>
                    <idcible>3</idcible>
                    <ratio>2</ratio>
                    <typeratio>vitesse</typeratio>
                    <unlocked>false</unlocked>
                </pallier>
                <pallier>
                    <name>Milieu titulaire</name>
                    <logo>img/products/3/3.png</logo>
                    <seuil>50</seuil>
                    <idcible>3</idcible>
                    <ratio>3</ratio>
                    <typeratio>gain</typeratio>
                    <unlocked>false</unlocked>
                </pallier>
                <pallier>
                    <name>Coup franc décisif</name>
                    <logo>img/products/3/4.png</logo>
                    <seuil>75</seuil>
                    <idcible>3</idcible>
                    <ratio>3</ratio>
                    <typeratio>vitesse</typeratio>
                    <unlocked>false</unlocked>
                </pallier>
                <pallier>
                    <name>Milieu de l'équipe nationale</name>
                    <logo>img/products/3/5.png</logo>
                    <seuil>100</seuil>
                    <idcible>3</idcible>
                    <ratio>3</ratio>
                    <typeratio>gain</typeratio>
                    <unlocked>false</unlocked>
                </pallier>
                <pallier>
                    <name>Le geste technique de l'année</name>
                    <logo>img/products/3/6.png</logo>
                    <seuil>150</seuil>
                    <idcible>3</idcible>
                    <ratio>2</ratio>
                    <typeratio>gain</typeratio>
                    <unlocked>false</unlocked>
                </pallier>
                <pallier>
                    <name>Milieu champion d'Europe</name>
                    <logo>img/products/3/7.png</logo>
                    <seuil>200</seuil>
                    <idcible>3</idcible>
                    <ratio>2</ratio>
                    <typeratio>gain</typeratio>
                    <unlocked>false</unlocked>
                </pallier>
                <pallier>
                    <name>Milieu champion du Monde</name>
                    <logo>img/products/3/8.png</logo>
                    <seuil>300</seuil>
                    <idcible>3</idcible>
                    <ratio>3</ratio>
                    <typeratio>vitesse</typeratio>
                    <unlocked>false</unlocked>
                </pallier>
                <pallier>
                    <name>Meilleur milieu du monde</name>
                    <logo>img/products/3/9.png</logo>
                    <seuil>400</seuil>
                    <idcible>3</idcible>
                    <ratio>2</ratio>
                    <typeratio>vitesse</typeratio>
                    <unlocked>false</unlocked>
                </pallier>
            </palliers>
        </product>
        <product>
            <id>4</id>
            <name>Attaquant</name>
            <logo>img/products/4.png</logo>
            <cout>8640</cout>
            <croissance>13</croissance>
            <revenu>4320</revenu>
            <vitesse>600000</vitesse>
            <quantite>0</quantite>
            <timeleft>0</timeleft>
            <managerUnlocked>false</managerUnlocked>
            <palliers>
                <pallier>
                    <name>Attaquant réserviste</name>
                    <logo>null</logo>
                    <seuil>10</seuil>
                    <idcible>4</idcible>
                    <ratio>1.5</ratio>
                    <typeratio>gain</typeratio>
                    <unlocked>false</unlocked>
                </pallier>
                <pallier>
                    <name>Attanquant remplaçant</name>
                    <logo>null</logo>
                    <seuil>25</seuil>
                    <idcible>4</idcible>
                    <ratio>2</ratio>
                    <typeratio>vitesse</typeratio>
                    <unlocked>false</unlocked>
                </pallier>
                <pallier>
                    <name>Attaquant titulaire</name>
                    <logo>null</logo>
                    <seuil>50</seuil>
                    <idcible>4</idcible>
                    <ratio>3</ratio>
                    <typeratio>vitesse</typeratio>
                    <unlocked>false</unlocked>
                </pallier>
                <pallier>
                    <name>Frappe de mule</name>
                    <logo>null</logo>
                    <seuil>75</seuil>
                    <idcible>4</idcible>
                    <ratio>3</ratio>
                    <typeratio>gain</typeratio>
                    <unlocked>false</unlocked>
                </pallier>
                <pallier>
                    <name>Attaquant de l'équipe nationale</name>
                    <logo>null</logo>
                    <seuil>100</seuil>
                    <idcible>4</idcible>
                    <ratio>3</ratio>
                    <typeratio>vitesse</typeratio>
                    <unlocked>false</unlocked>
                </pallier>
                <pallier>
                    <name>But de l'année</name>
                    <logo>null</logo>
                    <seuil>150</seuil>
                    <idcible>4</idcible>
                    <ratio>2</ratio>
                    <typeratio>gain</typeratio>
                    <unlocked>false</unlocked>
                </pallier>
                <pallier>
                    <name>Attaquant champion d'Europe</name>
                    <logo>null</logo>
                    <seuil>200</seuil>
                    <idcible>4</idcible>
                    <ratio>2</ratio>
                    <typeratio>gain</typeratio>
                    <unlocked>false</unlocked>
                </pallier>
                <pallier>
                    <name>Attaquant champion du Monde</name>
                    <logo>null</logo>
                    <seuil>300</seuil>
                    <idcible>4</idcible>
                    <ratio>3</ratio>
                    <typeratio>vitesse</typeratio>
                    <unlocked>false</unlocked>
                </pallier>
                <pallier>
                    <name>Meilleur attaquant du Monde</name>
                    <logo>null</logo>
                    <seuil>400</seuil>
                    <idcible>4</idcible>
                    <ratio>2</ratio>
                    <typeratio>vitesse</typeratio>
                    <unlocked>false</unlocked>
                </pallier>
            </palliers>
        </product>
        <product>
            <id>5</id>
            <name>Entraineur</name>
            <logo>img/products/5.png</logo>
            <cout>103680</cout>
            <croissance>12</croissance>
            <revenu>51840</revenu>
            <vitesse>1800000</vitesse>
            <quantite>0</quantite>
            <timeleft>0</timeleft>
            <managerUnlocked>false</managerUnlocked>
            <palliers>
                <pallier>
                    <name>Entraineur district</name>
                    <logo>null</logo>
                    <seuil>10</seuil>
                    <idcible>5</idcible>
                    <ratio>1.5</ratio>
                    <typeratio>gain</typeratio>
                    <unlocked>false</unlocked>
                </pallier>
                <pallier>
                    <name>Entraineur professionel</name>
                    <logo>null</logo>
                    <seuil>25</seuil>
                    <idcible>5</idcible>
                    <ratio>2</ratio>
                    <typeratio>vitesse</typeratio>
                    <unlocked>false</unlocked>
                </pallier>
                <pallier>
                    <name>Entraineur champion national</name>
                    <logo>null</logo>
                    <seuil>50</seuil>
                    <idcible>5</idcible>
                    <ratio>3</ratio>
                    <typeratio>gain</typeratio>
                    <unlocked>false</unlocked>
                </pallier>
                <pallier>
                    <name>Un remplacement victorieux</name>
                    <logo>null</logo>
                    <seuil>75</seuil>
                    <idcible>5</idcible>
                    <ratio>3</ratio>
                    <typeratio>vitesse</typeratio>
                    <unlocked>false</unlocked>
                </pallier>
                <pallier>
                    <name>Selectioneur national</name>
                    <logo>null</logo>
                    <seuil>100</seuil>
                    <idcible>5</idcible>
                    <ratio>3</ratio>
                    <typeratio>vitesse</typeratio>
                    <unlocked>false</unlocked>
                </pallier>
                <pallier>
                    <name>Une selection qui convientà tout le monde</name>
                    <logo>null</logo>
                    <seuil>150</seuil>
                    <idcible>5</idcible>
                    <ratio>2</ratio>
                    <typeratio>gain</typeratio>
                    <unlocked>false</unlocked>
                </pallier>
                <pallier>
                    <name>Selectionneur champion d'Europe</name>
                    <logo>null</logo>
                    <seuil>200</seuil>
                    <idcible>5</idcible>
                    <ratio>2</ratio>
                    <typeratio>vitesse</typeratio>
                    <unlocked>false</unlocked>
                </pallier>
                <pallier>
                    <name>Selectionneur champion du Monde</name>
                    <logo>null</logo>
                    <seuil>300</seuil>
                    <idcible>5</idcible>
                    <ratio>3</ratio>
                    <typeratio>vitesse</typeratio>
                    <unlocked>false</unlocked>
                </pallier>
                <pallier>
                    <name>Meilleur entraineur du Monde</name>
                    <logo>null</logo>
                    <seuil>400</seuil>
                    <idcible>5</idcible>
                    <ratio>2</ratio>
                    <typeratio>vitesse</typeratio>
                    <unlocked>false</unlocked>
                </pallier>
            </palliers>
        </product>
        <product>
            <id>6</id>
            <name>Stade</name>
            <logo>img/products/6.png</logo>
            <cout>1244160</cout>
            <croissance>11</croissance>
            <revenu>6220800</revenu>
            <vitesse>3600000</vitesse>
            <quantite>0</quantite>
            <timeleft>0</timeleft>
            <managerUnlocked>false</managerUnlocked>
            <palliers>
                <pallier>
                    <name>Salle Léo Lagrange</name>
                    <logo>img/products/6/1.png</logo>
                    <seuil>10</seuil>
                    <idcible>6</idcible>
                    <ratio>1.5</ratio>
                    <typeratio>gain</typeratio>
                    <unlocked>false</unlocked>
                </pallier>
                <pallier>
                    <name>Stade Raymond Kopa</name>
                    <logo>img/products/6/2.png</logo>
                    <seuil>25</seuil>
                    <idcible>6</idcible>
                    <ratio>2</ratio>
                    <typeratio>vitesse</typeratio>
                    <unlocked>false</unlocked>
                </pallier>
                <pallier>
                    <name>Et 50 000 places supplémentaires</name>
                    <logo>img/products/6/3.png</logo>
                    <seuil>50</seuil>
                    <idcible>6</idcible>
                    <ratio>3</ratio>
                    <typeratio>vitesse</typeratio>
                    <unlocked>false</unlocked>
                </pallier>
                <pallier>
                    <name>Grand'Stade de Lille</name>
                    <logo>img/products/6/4.png</logo>
                    <seuil>75</seuil>
                    <idcible>6</idcible>
                    <ratio>3</ratio>
                    <typeratio>vitesse</typeratio>
                    <unlocked>false</unlocked>
                </pallier>
                <pallier>
                    <name>Groupama Stadium</name>
                    <logo>img/products/6/5.png</logo>
                    <seuil>100</seuil>
                    <idcible>6</idcible>
                    <ratio>3</ratio>
                    <typeratio>vitesse</typeratio>
                    <unlocked>false</unlocked>
                </pallier>
                <pallier>
                    <name>Signal Iduna Park</name>
                    <logo>img/products/6/6.png</logo>
                    <seuil>150</seuil>
                    <idcible>6</idcible>
                    <ratio>2</ratio>
                    <typeratio>gain</typeratio>
                    <unlocked>false</unlocked>
                </pallier>
                <pallier>
                    <name>Stade de France</name>
                    <logo>img/products/6/7.png</logo>
                    <seuil>200</seuil>
                    <idcible>6</idcible>
                    <ratio>3</ratio>
                    <typeratio>vitesse</typeratio>
                    <unlocked>false</unlocked>
                </pallier>
                <pallier>
                    <name>Olympiastadion</name>
                    <logo>img/products/6/8.png</logo>
                    <seuil>300</seuil>
                    <idcible>6</idcible>
                    <ratio>3</ratio>
                    <typeratio>vitesse</typeratio>
                    <unlocked>false</unlocked>
                </pallier>
                <pallier>
                    <name>Stadio Bernabeu</name>
                    <logo>img/products/6/9.png</logo>
                    <seuil>400</seuil>
                    <idcible>6</idcible>
                    <ratio>2</ratio>
                    <typeratio>vitesse</typeratio>
                    <unlocked>false</unlocked>
                </pallier>
            </palliers>
        </product>
    </products>
    <allunlocks>
        <pallier>
            <name>Ma boulangerie, mon partenaire</name>
            <logo>img/allunlocks/1.png</logo>
            <seuil>10</seuil>
            <idcible>0</idcible>
            <ratio>3</ratio>
            <typeratio>gain</typeratio>
            <unlocked>false</unlocked>
        </pallier>
        <pallier>
            <name>Heineken, sponsor des remplaçants</name>
            <logo>img/allunlocks/2.png</logo>
            <seuil>25</seuil>
            <idcible>0</idcible>
            <ratio>3</ratio>
            <typeratio>gain</typeratio>
            <unlocked>false</unlocked>
        </pallier>
        <pallier>
            <name>Le club se paye la Matmut</name>
            <logo>img/allunlocks/3.png</logo>
            <seuil>50</seuil>
            <idcible>0</idcible>
            <ratio>3</ratio>
            <typeratio>gain</typeratio>
            <unlocked>false</unlocked>
        </pallier>
        <pallier>
            <name>On passe à la télé</name>
            <logo>img/allunlocks/4.png</logo>
            <seuil>75</seuil>
            <idcible>0</idcible>
            <ratio>3</ratio>
            <typeratio>gain</typeratio>
            <unlocked>false</unlocked>
        </pallier>
        <pallier>
            <name>Canal + mais en crypté</name>
            <logo>img/allunlocks/5.png</logo>
            <seuil>100</seuil>
            <idcible>0</idcible>
            <ratio>3</ratio>
            <typeratio>gain</typeratio>
            <unlocked>false</unlocked>
        </pallier>
        <pallier>
            <name>Merci Bein Sports</name>
            <logo>img/allunlocks/6.png</logo>
            <seuil>150</seuil>
            <idcible>0</idcible>
            <ratio>3</ratio>
            <typeratio>gain</typeratio>
            <unlocked>false</unlocked>
        </pallier>
        <pallier>
            <name>Autorisation de transfert de la FIFA</name>
            <logo>img/allunlocks/7.png</logo>
            <seuil>200</seuil>
            <idcible>0</idcible>
            <ratio>3</ratio>
            <typeratio>gain</typeratio>
            <unlocked>false</unlocked>
        </pallier>
        <pallier>
            <name>L'UEFA lève le fair-play financier</name>
            <logo>img/allunlocks/8.png</logo>
            <seuil>250</seuil>
            <idcible>0</idcible>
            <ratio>3</ratio>
            <typeratio>gain</typeratio>
            <unlocked>false</unlocked>
        </pallier>
        <pallier>
            <name>Poutine actionnaire</name>
            <logo>img/allunlocks/9.png</logo>
            <seuil>300</seuil>
            <idcible>0</idcible>
            <ratio>3</ratio>
            <typeratio>gain</typeratio>
            <unlocked>false</unlocked>
        </pallier>
        <pallier>
            <name>Un chinois majoritaire</name>
            <logo>img/allunlocks/10.png</logo>
            <seuil>400</seuil>
            <idcible>0</idcible>
            <ratio>3</ratio>
            <typeratio>gain</typeratio>
            <unlocked>false</unlocked>
        </pallier>
        <pallier>
            <name>Qatari à la rescousse</name>
            <logo>img/allunlocks/11.png</logo>
            <seuil>500</seuil>
            <idcible>0</idcible>
            <ratio>3</ratio>
            <typeratio>gain</typeratio>
            <unlocked>false</unlocked>
        </pallier>
    </allunlocks>
    <upgrades>
        <pallier>
            <name>Nouveaux gants</name>
            <logo>img/upgrades/1.png</logo>
            <seuil>250000</seuil>
            <idcible>1</idcible>
            <ratio>3</ratio>
            <typeratio>gain</typeratio>
            <unlocked>false</unlocked>
        </pallier>
        <pallier>
            <name>Travail de la tête</name>
            <logo>img/upgrades/2.png</logo>
            <seuil>500000</seuil>
            <idcible>2</idcible>
            <ratio>3</ratio>
            <typeratio>gain</typeratio>
            <unlocked>false</unlocked>
        </pallier>
        <pallier>
            <name>Passements de jambes améliorés</name>
            <logo>img/upgrades/3.png</logo>
            <seuil>1000000</seuil>
            <idcible>3</idcible>
            <ratio>3</ratio>
            <typeratio>gain</typeratio>
            <unlocked>false</unlocked>
        </pallier>
        <pallier>
            <name>Coup de reins devastateur</name>
            <logo>img/upgrades/4.png</logo>
            <seuil>5000000</seuil>
            <idcible>4</idcible>
            <ratio>3</ratio>
            <typeratio>gain</typeratio>
            <unlocked>false</unlocked>
        </pallier>
        <pallier>
            <name>Une glacière pour le match</name>
            <logo>img/upgrades/5.png</logo>
            <seuil>10000000</seuil>
            <idcible>5</idcible>
            <ratio>3</ratio>
            <typeratio>gain</typeratio>
            <unlocked>false</unlocked>
        </pallier>
        <pallier>
            <name>Un stade complètement couvert</name>
            <logo>img/upgrades/6.png</logo>
            <seuil>25000000</seuil>
            <idcible>6</idcible>
            <ratio>3</ratio>
            <typeratio>gain</typeratio>
            <unlocked>false</unlocked>
        </pallier>
        <pallier>
            <name>Un marketing florissant</name>
            <logo>img/upgrades/7.png</logo>
            <seuil>500000000</seuil>
            <idcible>0</idcible>
            <ratio>3</ratio>
            <typeratio>gain</typeratio>
            <unlocked>false</unlocked>
        </pallier>
        <pallier>
            <name>Arrêt d'une main</name>
            <logo>img/upgrades/8.png</logo>
            <seuil>10000000000</seuil>
            <idcible>1</idcible>
            <ratio>3</ratio>
            <typeratio>gain</typeratio>
            <unlocked>false</unlocked>
        </pallier>
        <pallier>
            <name>Epaule contre épaule</name>
            <logo>img/upgrades/9.png</logo>
            <seuil>50000000000</seuil>
            <idcible>2</idcible>
            <ratio>3</ratio>
            <typeratio>gain</typeratio>
            <unlocked>false</unlocked>
        </pallier>
        <pallier>
            <name>Touche dans la surface de reparation</name>
            <logo>img/upgrades/10.png</logo>
            <seuil>250000000000</seuil>
            <idcible>3</idcible>
            <ratio>3</ratio>
            <typeratio>gain</typeratio>
            <unlocked>false</unlocked>
        </pallier>
        <pallier>
            <name>Coup franc de 30m</name>
            <logo>img/upgrades/11.png</logo>
            <seuil>1000000000000</seuil>
            <idcible>4</idcible>
            <ratio>3</ratio>
            <typeratio>gain</typeratio>
            <unlocked>false</unlocked>
        </pallier>
        <pallier>
            <name>Interieur du pied</name>
            <logo>img/upgrades/12.png</logo>
            <seuil>20000000000000</seuil>
            <idcible>5</idcible>
            <ratio>3</ratio>
            <typeratio>gain</typeratio>
            <unlocked>false</unlocked>
        </pallier>
        <pallier>
            <name>Concert en levé de rideau</name>
            <logo>img/upgrades/13.png</logo>
            <seuil>50000000000000</seuil>
            <idcible>6</idcible>
            <ratio>3</ratio>
            <typeratio>gain</typeratio>
            <unlocked>false</unlocked>
        </pallier>
        <pallier>
            <name>Boutique en ligne</name>
            <logo>img/upgrades/14.png</logo>
            <seuil>100000000000000</seuil>
            <idcible>0</idcible>
            <ratio>3</ratio>
            <typeratio>gain</typeratio>
            <unlocked>false</unlocked>
        </pallier>
        <pallier>
            <name>Guy Roux adjoint</name>
            <logo>img/upgrades/15.png</logo>
            <seuil>500000000000000</seuil>
            <idcible>-1</idcible>
            <ratio>1</ratio>
            <typeratio>ange</typeratio>
            <unlocked>false</unlocked>
        </pallier>
    </upgrades>
    <angelupgrades>
        <pallier>
            <name>Lionel Messi</name>
            <logo>img/angels/messi.png</logo>
            <seuil>10000</seuil>
            <idcible>0</idcible>
            <ratio>3</ratio>
            <typeratio>gain</typeratio>
            <unlocked>false</unlocked>
        </pallier>
        <pallier>
            <name>Cristiano Ronaldo</name>
            <logo>img/angels/ronaldo.png</logo>
            <seuil>100000</seuil>
            <idcible>-1</idcible>
            <ratio>2</ratio>
            <typeratio>ange</typeratio>
            <unlocked>false</unlocked>
        </pallier>
        <pallier>
            <name>Ronaldinho</name>
            <logo>img/angels/ronaldinho.png</logo>
            <seuil>100000000</seuil>
            <idcible>0</idcible>
            <ratio>2</ratio>
            <typeratio>gain</typeratio>
            <unlocked>false</unlocked>
        </pallier>
        <pallier>
            <name>Zinedine Zidane</name>
            <logo>img/angels/zidane.png</logo>
            <seuil>100000000000</seuil>
            <idcible>-1</idcible>
            <ratio>3</ratio>
            <typeratio>ange</typeratio>
            <unlocked>false</unlocked>
        </pallier>
        <pallier>
            <name>George Best</name>
            <logo>img/angels/best.png</logo>
            <seuil>100000000000000</seuil>
            <idcible>0</idcible>
            <ratio>3</ratio>
            <typeratio>gain</typeratio>
            <unlocked>false</unlocked>
        </pallier>
        <pallier>
            <name>Frand Beckenbauer</name>
            <logo>img/angels/beckenbauer.png</logo>
            <seuil>100000000000000000</seuil>
            <idcible>-1</idcible>
            <ratio>2</ratio>
            <typeratio>ange</typeratio>
            <unlocked>false</unlocked>
        </pallier>
        <pallier>
            <name>Alfredo Di Stefano</name>
            <logo>img/angels/distefano.png</logo>
            <seuil>100000000000000000000</seuil>
            <idcible>0</idcible>
            <ratio>2</ratio>
            <typeratio>gain</typeratio>
            <unlocked>false</unlocked>
        </pallier>
        <pallier>
            <name>Diego Maradonna</name>
            <logo>img/angels/maradonna.png</logo>
            <seuil>100000000000000000000000</seuil>
            <idcible>-1</idcible>
            <ratio>4</ratio>
            <typeratio>ange</typeratio>
            <unlocked>false</unlocked>
        </pallier>
        <pallier>
            <name>Johan Cruif</name>
            <logo>img/angels/cruif.png</logo>
            <seuil>100000000000000000000000000</seuil>
            <idcible>0</idcible>
            <ratio>4</ratio>
            <typeratio>gain</typeratio>
            <unlocked>false</unlocked>
        </pallier>
        <pallier>
            <name>Pelé</name>
            <logo>img/angels/pele.png</logo>
            <seuil>100000000000000000</seuil>
            <idcible>-1</idcible>
            <ratio>5</ratio>
            <typeratio>ange</typeratio>
            <unlocked>false</unlocked>
        </pallier>
    </angelupgrades>
    <managers>
        <pallier>
            <name>Fabien Barthez</name>
            <logo>img/managers/barthez.png</logo>
            <seuil>1000</seuil>
            <idcible>1</idcible>
            <ratio>0</ratio>
            <typeratio>gain</typeratio>
            <unlocked>false</unlocked>
        </pallier>
        <pallier>
            <name>Laurent Blanc</name>
            <logo>img/managers/blanc.png</logo>
            <seuil>15000</seuil>
            <idcible>2</idcible>
            <ratio>0</ratio>
            <typeratio>gain</typeratio>
            <unlocked>false</unlocked>
        </pallier>
        <pallier>
            <name>Robert Pires</name>
            <logo>img/managers/pires.png</logo>
            <seuil>100000</seuil>
            <idcible>3</idcible>
            <ratio>0</ratio>
            <typeratio>gain</typeratio>
            <unlocked>false</unlocked>
        </pallier>
        <pallier>
            <name>Thierry Henry</name>
            <logo>img/managers/henry.png</logo>
            <seuil>500000</seuil>
            <idcible>4</idcible>
            <ratio>0</ratio>
            <typeratio>gain</typeratio>
            <unlocked>false</unlocked>
        </pallier>
        <pallier>
            <name>Aimé Jacquet</name>
            <logo>img/managers/jacquet.png</logo>
            <seuil>1200000</seuil>
            <idcible>5</idcible>
            <ratio>0</ratio>
            <typeratio>gain</typeratio>
            <unlocked>false</unlocked>
        </pallier>
        <pallier>
            <name>Stade de France</name>
            <logo>img/managers/sdf.png</logo>
            <seuil>10000000</seuil>
            <idcible>6</idcible>
            <ratio>0</ratio>
            <typeratio>gain</typeratio>
            <unlocked>false</unlocked>
        </pallier>
    </managers>
</world>